<?xml version="1.0" encoding="UTF-8"?>
<archetype-descriptor name="basic">
	<requiredProperties>
		<requiredProperty key="projectNaturalName"/>
		<requiredProperty key="projectNameOneWord"/>
	</requiredProperties>

	<fileSets>
		<fileSet filtered="false" packaged="false">
			<directory>etc</directory>
			<includes>
				<include>**/*</include>
			</includes>
		</fileSet>
		<fileSet filtered="false" packaged="false">
			<directory></directory>
			<includes>
				<include>gettingStarted.txt</include>
			</includes>
		</fileSet>
	</fileSets>
</archetype-descriptor>