<?xml version="1.0" encoding="ISO-8859-1"?>
<!DOCTYPE sqlMap
    PUBLIC "-//ibatis.apache.org//DTD SQL Map 2.0//EN"
    "http://ibatis.apache.org/dtd/sql-map-2.dtd">

<sqlMap namespace="refdb-core">
    <!-- Version: $Revision$ -->
    <!-- Source: $Source$ -->
    <!-- Date: $Date$ -->
    <!-- Author: $Author$ -->

    <!-- 
        Annotation related invocations
    -->
    <!-- 
        ATTENTION: Dynamic parts are only used due to badly implemented jdbc 
        driver from ibm, which does not support java.sql.Types.NULL!
    -->
    <insert id="insertAnnotation">
        insert into ANNOTATIONS (KEYTOREFERENCE, ANNOTATOR, GRADE, 
            CONTENT, WHENINSERTED, OPTIMISTICLOCKINGVERSION) 
            values (#keyToReference#, 
                <dynamic>
                    <isNotNull property="annotator">
                        #annotator#
                    </isNotNull>
                    <isNull property="annotator">
                        null
                    </isNull>
                    ,
                </dynamic>
                #grade#, #content,handler=clobHandler#, #whenInserted#, 
                #optimisticLockingVersion#)
        <selectKey resultClass="int" keyProperty="key">
            values IDENTITY_VAL_LOCAL()
        </selectKey>
    </insert>

    <update id="updateAnnotation">
        update ANNOTATIONS set KEYTOREFERENCE=#keyToReference#, 
            <dynamic>
                <isNotNull property="annotator">
                    ANNOTATOR=#annotator#
                </isNotNull>
                <isNull property="annotator">
                    ANNOTATOR=null
                </isNull>
                ,
            </dynamic>
            GRADE=#grade#, CONTENT=#content,handler=clobHandler#, 
            OPTIMISTICLOCKINGVERSION=OPTIMISTICLOCKINGVERSION+1 
            where KEYID=#key# 
                and OPTIMISTICLOCKINGVERSION=#optimisticLockingVersion#
    </update>
</sqlMap>
